ncnc/__init__.py
ncnc/c_value.py
ncnc/logging.py
ncnc/nc_value.py
ncnc-1.0.0.dist-info/LICENSE
ncnc-1.0.0.dist-info/METADATA
ncnc-1.0.0.dist-info/WHEEL
ncnc-1.0.0.dist-info/RECORD
