Metadata-Version: 2.1
Name: ncnc
Version: 1.0.0
Summary: An implementation of C-value and NC-value methods
License: MIT
Author: Jun Harashima
Requires-Python: >=3.10,<4.0
Classifier: License :: OSI Approved :: MIT License
Classifier: Programming Language :: Python :: 3
Classifier: Programming Language :: Python :: 3.10
Classifier: Programming Language :: Python :: 3.11
Requires-Dist: pandas (>=2.0.1,<3.0.0)
Requires-Dist: tqdm (>=4.65.0,<5.0.0)
